{
  "$schema": "https://zed.dev/schema/themes/v0.2.0.json",
  "name": "Aura 2026",
  "author": "Dalton Menezes <daltonmenezes@outlook.com>",
  "themes": [
    {
      "appearance": "dark",
      "name": "Aura Cyan 2026",
      "style": {
        "accents": [
          "#67E8F9",
          "#61FFCA",
          "#67E8F9",
          "#F694FF",
          "#22D3EE",
          "#FF6767",
          "#FFCA85"
        ],
        "background": "#09080D",
        "background.appearance": "opaque",
        "drop_target.background": "#0891B2",
        "editor.active_line.background": "#6D6D6D33",
        "editor.active_line_number": "#F2F0F5",
        "editor.hover_line_number": "#ADACAE",
        "editor.active_wrap_guide": "#4D4D4D",
        "editor.background": "#09080D",
        "editor.document_highlight.bracket_background": "#0891B21A",
        "editor.document_highlight.read_background": "#0891B2DD",
        "editor.document_highlight.write_background": "#0891B2DD",
        "editor.foreground": "#DDD9E7",
        "editor.gutter.background": "#09080D",
        "editor.highlighted_line.background": "#6D6D6D33",
        "editor.indent_guide": "#4D4D4D",
        "editor.indent_guide_active": "#6D6D6D",
        "editor.invisible": "#6D6D6D",
        "editor.line_number": "#6D6D6D33",
        "editor.subheader.background": "#0A090F",
        "editor.wrap_guide": "#4D4D4D",
        "elevated_surface.background": "#0A090F",
        "pane.focused_border": "#F2F0F5",
        "pane_group.border": "#000000",
        "panel.background": "#0A090F",
        "panel.focused_border": "#F2F0F5",
        "panel.indent_guide": "#4D4D4D",
        "panel.indent_guide_active": "#6D6D6D",
        "panel.indent_guide_hover": "#241F31",
        "search.match_background": "#0891B2DD",
        "search.active_match_background": "#FFCA8524",
        "status_bar.background": "#0A090F",
        "surface.background": "#09080D",
        "tab.active_background": "#09080D",
        "tab.inactive_background": "#0A090F",
        "tab_bar.background": "#0A090F",
        "title_bar.background": "#0A090F",
        "title_bar.inactive_background": "#0F0D16",
        "toolbar.background": "#09080D",
        "text": "#F2F0F5",
        "text.accent": "#67E8F9",
        "text.disabled": "#6D6D6D",
        "text.muted": "#6D6D6D",
        "text.placeholder": "#67E8F97F",
        "border": "#000000",
        "border.variant": "#67E8F97F",
        "border.focused": "#6D6D6D33",
        "border.selected": "#67E8F9",
        "border.disabled": "#6D6D6D",
        "border.transparent": "#61FFCA",
        "element.active": "#0891B2DD",
        "element.background": "#0A090F",
        "element.disabled": "#6D6D6D",
        "element.hover": "#15121C",
        "element.selected": "#0891B2DD",
        "ghost_element.active": "#6D6D6D33",
        "ghost_element.background": "#00000000",
        "ghost_element.disabled": "#6D6D6D",
        "ghost_element.hover": "#241F31",
        "ghost_element.selected": "#15121C",
        "icon": "#4D4D4D",
        "icon.accent": "#61FFCA",
        "icon.disabled": "#6D6D6D",
        "icon.muted": "#ADACAE",
        "icon.placeholder": "#67E8F97F",
        "scrollbar.thumb.border": "#241F31",
        "scrollbar.thumb.hover_background": "#6D6D6D66",
        "scrollbar.thumb.background": "#6D6D6D33",
        "scrollbar.track.border": "#241F31",
        "scrollbar.track.background": "#00000000",
        "terminal.ansi.background": "#09080D",
        "terminal.ansi.black": "#0A090F",
        "terminal.ansi.blue": "#22D3EE",
        "terminal.ansi.bright_black": "#6D6D6D",
        "terminal.ansi.bright_blue": "#67E8F9",
        "terminal.ansi.bright_cyan": "#82E2FF",
        "terminal.ansi.bright_green": "#9DFF65",
        "terminal.ansi.bright_magenta": "#F694FF",
        "terminal.ansi.bright_red": "#FF6767",
        "terminal.ansi.bright_white": "#F2F0F5",
        "terminal.ansi.bright_yellow": "#FFCA85",
        "terminal.ansi.cyan": "#72DCC6",
        "terminal.ansi.dim_black": "#4D4D4D",
        "terminal.ansi.dim_blue": "#0891B2",
        "terminal.ansi.dim_cyan": "#72DCC6",
        "terminal.ansi.dim_green": "#61FFCA",
        "terminal.ansi.dim_magenta": "#7C3AED",
        "terminal.ansi.dim_red": "#FF6767",
        "terminal.ansi.dim_white": "#ADACAE",
        "terminal.ansi.dim_yellow": "#FFCA85",
        "terminal.ansi.green": "#61FFCA",
        "terminal.ansi.magenta": "#C17AC8",
        "terminal.ansi.red": "#FF6767",
        "terminal.ansi.white": "#DDD9E7",
        "terminal.ansi.yellow": "#FFCA85",
        "terminal.background": "#09080D",
        "terminal.bright_foreground": "#F2F0F5",
        "terminal.dim_foreground": "#ADACAE",
        "terminal.foreground": "#DDD9E7",
        "error": "#FF6767",
        "error.background": "#FF676724",
        "error.border": "#FF6767",
        "hint": "#6D6D6D",
        "hint.background": "#1B1724CC",
        "hint.border": "#241F31",
        "info": "#22D3EE",
        "info.background": "#22D3EE1F",
        "info.border": "#22D3EE",
        "link_text.hover": "#61FFCA",
        "version_control.added": "#61FFCA",
        "version_control.modified": "#67E8F9",
        "version_control.deleted": "#FF6767",
        "version_control.renamed": "#22D3EE",
        "version_control.conflict": "#67E8F9",
        "version_control.ignored": "#6D6D6D",
        "version_control.word_added": "#61FFCA1F",
        "version_control.word_deleted": "#FF676724",
        "version_control.conflict_marker.ours": "#61FFCA1F",
        "version_control.conflict_marker.theirs": "#0891B21A",
        "predictive": "#6D6D6D",
        "predictive.background": "#0891B21A",
        "predictive.border": "#15121C",
        "renamed": "#22D3EE",
        "renamed.background": "#22D3EE1F",
        "renamed.border": "#22D3EE",
        "success": "#61FFCA",
        "success.background": "#61FFCA1F",
        "success.border": "#61FFCA",
        "unreachable": "#FF6767",
        "unreachable.background": "#1B1724CC",
        "unreachable.border": "#FF6767",
        "warning": "#67E8F9",
        "warning.background": "#FFCA8524",
        "warning.border": "#67E8F9",
        "conflict": "#67E8F9",
        "conflict.background": "#0891B21A",
        "conflict.border": "#67E8F9",
        "created": "#61FFCA",
        "created.background": "#61FFCA1F",
        "created.border": "#61FFCA",
        "deleted": "#FF6767",
        "deleted.background": "#FF676724",
        "deleted.border": "#FF6767",
        "hidden": "#6D6D6D",
        "hidden.background": "#1B1724CC",
        "hidden.border": "#6D6D6D",
        "ignored": "#6D6D6D",
        "ignored.background": "#1B1724CC",
        "ignored.border": "#6D6D6D",
        "modified": "#67E8F9",
        "modified.background": "#FFCA8524",
        "modified.border": "#67E8F9",
        "players": [
          {
            "cursor": "#67E8F9",
            "background": "#67E8F9",
            "selection": "#0891B2DD"
          },
          {
            "cursor": "#61FFCA",
            "background": "#61FFCA",
            "selection": "#2958487f"
          },
          {
            "cursor": "#67E8F9",
            "background": "#67E8F9",
            "selection": "#2c51567f"
          },
          {
            "cursor": "#61FFCA",
            "background": "#61FFCA",
            "selection": "#2958487f"
          },
          {
            "cursor": "#FF6767",
            "background": "#FF6767",
            "selection": "#582b2b7f"
          },
          {
            "cursor": "#F694FF",
            "background": "#F694FF",
            "selection": "#573a5a7f"
          },
          {
            "cursor": "#22D3EE",
            "background": "#22D3EE",
            "selection": "#15474f7f"
          }
        ],
        "syntax": {
          "attribute": {
            "color": "#22D3EE",
            "font_style": null,
            "font_weight": null
          },
          "boolean": {
            "color": "#22D3EE",
            "font_style": null,
            "font_weight": null
          },
          "comment": {
            "color": "#6D6D6D",
            "font_style": null,
            "font_weight": null
          },
          "comment.doc": {
            "color": "#B8B4D6",
            "font_style": null,
            "font_weight": null
          },
          "comment.documentation": {
            "color": "#B8B4D6",
            "font_style": null,
            "font_weight": null
          },
          "constant": {
            "color": "#22D3EE",
            "font_style": null,
            "font_weight": null
          },
          "constant.builtin": {
            "color": "#F694FF",
            "font_style": null,
            "font_weight": null
          },
          "constant.numeric": {
            "color": "#FFCA85",
            "font_style": null,
            "font_weight": null
          },
          "constructor": {
            "color": "#22D3EE",
            "font_style": null,
            "font_weight": null
          },
          "decorator": {
            "color": "#F694FF",
            "font_style": null,
            "font_weight": null
          },
          "embedded": {
            "color": "#DDD9E7",
            "font_style": null,
            "font_weight": null
          },
          "emphasis": {
            "color": "#67E8F9",
            "font_style": null,
            "font_weight": null
          },
          "emphasis.strong": {
            "color": "#67E8F9",
            "font_style": null,
            "font_weight": null
          },
          "class": {
            "color": "#22D3EE",
            "font_style": null,
            "font_weight": null
          },
          "enum": {
            "color": "#22D3EE",
            "font_style": null,
            "font_weight": null
          },
          "enumMember": {
            "color": "#22D3EE",
            "font_style": null,
            "font_weight": null
          },
          "function": {
            "color": "#67E8F9",
            "font_style": null,
            "font_weight": null
          },
          "function.definition": {
            "color": "#67E8F9",
            "font_style": null,
            "font_weight": null
          },
          "function.method": {
            "color": "#67E8F9",
            "font_style": null,
            "font_weight": null
          },
          "function.special": {
            "color": "#FFCA85",
            "font_style": null,
            "font_weight": null
          },
          "function.kwargs": {
            "color": "#B8B4D6",
            "font_style": "italic",
            "font_weight": null
          },
          "hint": {
            "color": "#22D3EE",
            "font_style": null,
            "font_weight": null
          },
          "interface": {
            "color": "#22D3EE",
            "font_style": "italic",
            "font_weight": null
          },
          "keyword": {
            "color": "#67E8F9",
            "font_style": null,
            "font_weight": null
          },
          "keyword.control": {
            "color": "#67E8F9",
            "font_style": null,
            "font_weight": null
          },
          "keyword.operator": {
            "color": "#67E8F9",
            "font_style": null,
            "font_weight": null
          },
          "keyword.return": {
            "color": "#67E8F9",
            "font_style": null,
            "font_weight": null
          },
          "link_text": {
            "color": "#22D3EE",
            "font_style": null,
            "font_weight": null
          },
          "link_uri": {
            "color": "#22D3EE",
            "font_style": null,
            "font_weight": null
          },
          "number": {
            "color": "#FFCA85",
            "font_style": null,
            "font_weight": null
          },
          "method": {
            "color": "#67E8F9",
            "font_style": null,
            "font_weight": null
          },
          "module": {
            "color": "#82E2FF",
            "font_style": null,
            "font_weight": null
          },
          "namespace": {
            "color": "#82E2FF",
            "font_style": null,
            "font_weight": null
          },
          "operator": {
            "color": "#67E8F9",
            "font_style": null,
            "font_weight": null
          },
          "parameter": {
            "color": "#B8B4D6",
            "font_style": "italic",
            "font_weight": null
          },
          "label": {
            "color": "#F694FF",
            "font_style": null,
            "font_weight": null
          },
          "preproc": {
            "color": "#22D3EE",
            "font_style": null,
            "font_weight": null
          },
          "preproc.directive": {
            "color": "#22D3EE",
            "font_style": null,
            "font_weight": null
          },
          "predictive": {
            "color": "#ADACAE",
            "font_style": "italic",
            "font_weight": null
          },
          "primary": {
            "color": "#DDD9E7",
            "font_style": null,
            "font_weight": null
          },
          "property": {
            "color": "#F694FF",
            "font_style": null,
            "font_weight": null
          },
          "property.definition": {
            "color": "#F694FF",
            "font_style": null,
            "font_weight": null
          },
          "punctuation": {
            "color": "#DDD9E7",
            "font_style": null,
            "font_weight": null
          },
          "punctuation.bracket": {
            "color": "#ADACAE",
            "font_style": null,
            "font_weight": null
          },
          "punctuation.delimiter": {
            "color": "#ADACAE",
            "font_style": null,
            "font_weight": null
          },
          "punctuation.list_marker": {
            "color": "#E0A6FF",
            "font_style": null,
            "font_weight": null
          },
          "punctuation.markup": {
            "color": "#F694FF",
            "font_style": null,
            "font_weight": null
          },
          "punctuation.special": {
            "color": "#FF6767",
            "font_style": null,
            "font_weight": null
          },
          "selector": {
            "color": "#9DFF65",
            "font_style": null,
            "font_weight": null
          },
          "selector.pseudo": {
            "color": "#9DFF65",
            "font_style": null,
            "font_weight": null
          },
          "string": {
            "color": "#61FFCA",
            "font_style": null,
            "font_weight": null
          },
          "string.doc": {
            "color": "#61FFCA",
            "font_style": null,
            "font_weight": null
          },
          "string.escape": {
            "color": "#FFCA85",
            "font_style": null,
            "font_weight": null
          },
          "string.regex": {
            "color": "#FFCA85",
            "font_style": null,
            "font_weight": null
          },
          "string.special": {
            "color": "#FFCA85",
            "font_style": null,
            "font_weight": null
          },
          "string.special.symbol": {
            "color": "#FFCA85",
            "font_style": null,
            "font_weight": null
          },
          "tag": {
            "color": "#61FFCA",
            "font_style": null,
            "font_weight": null
          },
          "text.literal": {
            "color": "#61FFCA",
            "font_style": null,
            "font_weight": null
          },
          "title": {
            "color": "#E0A6FF",
            "font_style": null,
            "font_weight": null
          },
          "type": {
            "color": "#22D3EE",
            "font_style": null,
            "font_weight": null
          },
          "type.class": {
            "color": "#22D3EE",
            "font_style": null,
            "font_weight": null
          },
          "type.builtin": {
            "color": "#22D3EE",
            "font_style": null,
            "font_weight": null
          },
          "type.defaultLibrary": {
            "color": "#22D3EE",
            "font_style": null,
            "font_weight": null
          },
          "type.interface": {
            "color": "#22D3EE",
            "font_style": "italic",
            "font_weight": null
          },
          "typeParameter": {
            "color": "#22D3EE",
            "font_style": "italic",
            "font_weight": null
          },
          "variable": {
            "color": "#DDD9E7",
            "font_style": null,
            "font_weight": null
          },
          "variable.builtin": {
            "color": "#F694FF",
            "font_style": null,
            "font_weight": null
          },
          "variable.member": {
            "color": "#F694FF",
            "font_style": null,
            "font_weight": null
          },
          "variable.mutable": {
            "color": "#DDD9E7",
            "font_style": null,
            "font_weight": null
          },
          "variable.parameter": {
            "color": "#B8B4D6",
            "font_style": "italic",
            "font_weight": null
          },
          "variable.defaultLibrary": {
            "color": "#F694FF",
            "font_style": null,
            "font_weight": null
          },
          "variable.readonly": {
            "color": "#F694FF",
            "font_style": null,
            "font_weight": null
          },
          "variable.special": {
            "color": "#F694FF",
            "font_style": null,
            "font_weight": null
          },
          "property.readonly": {
            "color": "#F694FF",
            "font_style": null,
            "font_weight": null
          },
          "struct": {
            "color": "#22D3EE",
            "font_style": null,
            "font_weight": null
          },
          "variant": {
            "color": "#22D3EE",
            "font_style": null,
            "font_weight": null
          }
        }
      }
    }
  ]
}
